.editorconfig
.gitignore
.gitlab-ci.yml
README.rst
publish.settings.sh
publish.sh
pyproject.toml
tsconfig.json
.idea/modules.xml
.idea/peek-plugin-docdb-generic-menu.iml
.idea/inspectionProfiles/Project_Default.xml
.idea/inspectionProfiles/profiles_settings.xml
peek_plugin_docdb_generic_menu/__init__.py
peek_plugin_docdb_generic_menu/plugin_package.json
peek_plugin_docdb_generic_menu.egg-info/PKG-INFO
peek_plugin_docdb_generic_menu.egg-info/SOURCES.txt
peek_plugin_docdb_generic_menu.egg-info/dependency_links.txt
peek_plugin_docdb_generic_menu.egg-info/requires.txt
peek_plugin_docdb_generic_menu.egg-info/top_level.txt
peek_plugin_docdb_generic_menu/_private/PluginNames.py
peek_plugin_docdb_generic_menu/_private/__init__.py
peek_plugin_docdb_generic_menu/_private/alembic.ini
peek_plugin_docdb_generic_menu/_private/admin-app/docDbGenericMenu.module.ts
peek_plugin_docdb_generic_menu/_private/admin-app/components/docdb-generic-menu-admin-page/docdb-generic-menu-admin-page.component.html
peek_plugin_docdb_generic_menu/_private/admin-app/components/docdb-generic-menu-admin-page/docdb-generic-menu-admin-page.component.scss
peek_plugin_docdb_generic_menu/_private/admin-app/components/docdb-generic-menu-admin-page/docdb-generic-menu-admin-page.component.ts
peek_plugin_docdb_generic_menu/_private/admin-app/components/edit-docdb-generic-menu-table/edit.component.html
peek_plugin_docdb_generic_menu/_private/admin-app/components/edit-docdb-generic-menu-table/edit.component.scss
peek_plugin_docdb_generic_menu/_private/admin-app/components/edit-docdb-generic-menu-table/edit.component.ts
peek_plugin_docdb_generic_menu/_private/admin-app/components/edit-setting-table/edit.component.html
peek_plugin_docdb_generic_menu/_private/admin-app/components/edit-setting-table/edit.component.scss
peek_plugin_docdb_generic_menu/_private/admin-app/components/edit-setting-table/edit.component.ts
peek_plugin_docdb_generic_menu/_private/alembic/__init__.py
peek_plugin_docdb_generic_menu/_private/alembic/env.py
peek_plugin_docdb_generic_menu/_private/alembic/script.py.mako
peek_plugin_docdb_generic_menu/_private/alembic/versions/1ac6c325c7e5_added_condition.py
peek_plugin_docdb_generic_menu/_private/alembic/versions/1f288982a4e2_initial.py
