Metadata-Version: 2.4
Name: peek-plugin-docdb-generic-menu
Version: 5.0.4
Summary: Peek Plugin DocDB Generic Menu - generic menus in Peek DocDB popups
Author-email: Synerty <contact@synerty.com>
Project-URL: Homepage, https://github.com/Synerty/peek-plugin-docdb-generic-menu
Keywords: Peek,Python,Platform,synerty
Requires-Dist: peek-plugin-base==5.0.4
